{
  "main": {
    "id": "09ece0d4603d0916",
    "type": "split",
    "children": [
      {
        "id": "f2fe10c043686c80",
        "type": "tabs",
        "children": [
          {
            "id": "bc4965b64c6c3bdc",
            "type": "leaf",
            "state": {
              "type": "markdown",
              "state": {
                "file": "gemini.md",
                "mode": "source",
                "source": false
              },
              "icon": "lucide-file",
              "title": "gemini"
            }
          }
        ]
      }
    ],
    "direction": "vertical"
  },
  "left": {
    "id": "b93aef66d6208109",
    "type": "split",
    "children": [
      {
        "id": "b9811e8259969da3",
        "type": "tabs",
        "children": [
          {
            "id": "cb2745200b9ef79f",
            "type": "leaf",
            "state": {
              "type": "file-explorer",
              "state": {
                "sortOrder": "alphabetical",
                "autoReveal": false
              },
              "icon": "lucide-folder-closed",
              "title": "Files"
            }
          },
          {
            "id": "8f931d5d5b6bca9e",
            "type": "leaf",
            "state": {
              "type": "search",
              "state": {
                "query": "",
                "matchingCase": false,
                "explainSearch": false,
                "collapseAll": false,
                "extraContext": false,
                "sortOrder": "alphabetical"
              },
              "icon": "lucide-search",
              "title": "Search"
            }
          },
          {
            "id": "d6713a35815d78f5",
            "type": "leaf",
            "state": {
              "type": "bookmarks",
              "state": {},
              "icon": "lucide-bookmark",
              "title": "Bookmarks"
            }
          }
        ]
      }
    ],
    "direction": "horizontal",
    "width": 300
  },
  "right": {
    "id": "f73a6d8682e3fff4",
    "type": "split",
    "children": [
      {
        "id": "01ce9aeaf42e2622",
        "type": "tabs",
        "children": [
          {
            "id": "f32a2fb00757a1ea",
            "type": "leaf",
            "state": {
              "type": "backlink",
              "state": {
                "file": "scratchpad/MOBILE_CLIENT_PROCESSES.md",
                "collapseAll": false,
                "extraContext": false,
                "sortOrder": "alphabetical",
                "showSearch": false,
                "searchQuery": "",
                "backlinkCollapsed": false,
                "unlinkedCollapsed": true
              },
              "icon": "links-coming-in",
              "title": "Backlinks for MOBILE_CLIENT_PROCESSES"
            }
          },
          {
            "id": "a203f31f5345eea3",
            "type": "leaf",
            "state": {
              "type": "outgoing-link",
              "state": {
                "file": "scratchpad/MOBILE_CLIENT_PROCESSES.md",
                "linksCollapsed": false,
                "unlinkedCollapsed": true
              },
              "icon": "links-going-out",
              "title": "Outgoing links from MOBILE_CLIENT_PROCESSES"
            }
          },
          {
            "id": "68a9dc1990d931e9",
            "type": "leaf",
            "state": {
              "type": "tag",
              "state": {
                "sortOrder": "frequency",
                "useHierarchy": true,
                "showSearch": false,
                "searchQuery": ""
              },
              "icon": "lucide-tags",
              "title": "Tags"
            }
          },
          {
            "id": "71f59436803dbde3",
            "type": "leaf",
            "state": {
              "type": "all-properties",
              "state": {
                "sortOrder": "frequency",
                "showSearch": false,
                "searchQuery": ""
              },
              "icon": "lucide-archive",
              "title": "All properties"
            }
          },
          {
            "id": "f39415e2355fd6a2",
            "type": "leaf",
            "state": {
              "type": "outline",
              "state": {
                "file": "scratchpad/MOBILE_CLIENT_PROCESSES.md",
                "followCursor": false,
                "showSearch": false,
                "searchQuery": ""
              },
              "icon": "lucide-list",
              "title": "Outline of MOBILE_CLIENT_PROCESSES"
            }
          }
        ]
      }
    ],
    "direction": "horizontal",
    "width": 300,
    "collapsed": true
  },
  "left-ribbon": {
    "hiddenItems": {
      "switcher:Open quick switcher": false,
      "graph:Open graph view": false,
      "canvas:Create new canvas": false,
      "daily-notes:Open today's daily note": false,
      "templates:Insert template": false,
      "command-palette:Open command palette": false,
      "bases:Create new base": false
    }
  },
  "active": "bc4965b64c6c3bdc",
  "lastOpenFiles": [
    "Untitled.md",
    "gemini.md",
    "types.d.ts",
    "node_modules/viem/node_modules/ox/_esm/core/internal",
    "node_modules/viem/node_modules/ox/_esm/core/RpcResponse.js",
    "node_modules/viem/node_modules/ox/_esm/core/RpcRequest.js",
    "node_modules/viem/node_modules/ox/_esm/core/Rlp.js",
    "node_modules/viem/node_modules/ox/_esm/core/PublicKey.js",
    "node_modules/viem/node_modules/ox/_esm/core/Provider.js",
    "node_modules/viem/node_modules/ox/_esm/core/PersonalMessage.js",
    "node_modules/viem/node_modules/ox/_esm/core/P256.js",
    "node_modules/viem/node_modules/ox/_esm/core/Mnemonic.js",
    "Key Functionality.md",
    "nav.png",
    "SCR-20251203-olcb.png",
    "splash.png",
    "SCR-20251203-okxb.png",
    "scratchpad/MOBILE_CLIENT_PROCESSES.md"
  ]
}